README.md
setup.py
tracing/__init__.py
tracing.egg-info/PKG-INFO
tracing.egg-info/SOURCES.txt
tracing.egg-info/dependency_links.txt
tracing.egg-info/top_level.txt