Metadata-Version: 1.1
Name: tracing
Version: 0.1.2
Summary: Utilities for tracing program execution.
Home-page: https://github.com/hchasestevens/tracing
Author: H. Chase Stevens
Author-email: chase@chasestevens.com
License: MIT
Keywords: tracing debug ipython
Platform: UNKNOWN
Classifier: Development Status :: 3 - Alpha
Classifier: Programming Language :: Python
Classifier: Programming Language :: Python :: 2
Classifier: Programming Language :: Python :: 2.7
Classifier: Programming Language :: Python :: 3
Classifier: Intended Audience :: Developers
Classifier: Operating System :: OS Independent
Classifier: License :: OSI Approved :: MIT License
Classifier: Natural Language :: English
